{
  "inn1": {
    "score": 142,
    "for": 10,
    "overs": 20,
    "extras": {
      "total_extras": 1,
      "wides": 1,
      "no_balls": 0,
      "lbs": 0,
      "byes": 0
    },
    "batting": [
      {
        "id": 208,
        "batted": true,
        "pos": 1,
        "runs": 18,
        "balls": 21,
        "c0": 9,
        "c1": 10,
        "c2": 0,
        "c3": 0,
        "c4": 2,
        "c6": 0,
        "method": "c",
        "fielder": "rahmat",
        "bowler": 113,
        "not_out": false
      },
      {
        "id": 29,
        "batted": true,
        "pos": 2,
        "runs": 6,
        "balls": 2,
        "c0": 1,
        "c1": 0,
        "c2": 0,
        "c3": 0,
        "c4": 0,
        "c6": 1,
        "method": "c",
        "fielder": "ikram",
        "bowler": 164,
        "not_out": false
      },
      {
        "id": 261,
        "batted": true,
        "pos": 3,
        "runs": 15,
        "balls": 18,
        "c0": 8,
        "c1": 9,
        "c2": 0,
        "c3": 0,
        "c4": 0,
        "c6": 1,
        "method": "c",
        "fielder": "mujeeb",
        "bowler": 112,
        "not_out": false
      },
      {
        "id": 31,
        "batted": true,
        "pos": 4,
        "runs": 25,
        "balls": 24,
        "c0": 9,
        "c1": 11,
        "c2": 1,
        "c3": 0,
        "c4": 3,
        "c6": 0,
        "method": "b",
        "fielder": null,
        "bowler": 164,
        "not_out": false
      },
      {
        "id": 32,
        "batted": true,
        "pos": 5,
        "runs": 7,
        "balls": 6,
        "c0": 2,
        "c1": 3,
        "c2": 0,
        "c3": 0,
        "c4": 1,
        "c6": 0,
        "method": "b",
        "fielder": null,
        "bowler": 112,
        "not_out": false
      },
      {
        "id": 308,
        "batted": true,
        "pos": 6,
        "runs": 0,
        "balls": 1,
        "c0": 1,
        "c1": 0,
        "c2": 0,
        "c3": 0,
        "c4": 0,
        "c6": 0,
        "method": "c",
        "fielder": "ikram",
        "bowler": 112,
        "not_out": false
      },
      {
        "id": 301,
        "batted": true,
        "pos": 7,
        "runs": 36,
        "balls": 21,
        "c0": 7,
        "c1": 8,
        "c2": 1,
        "c3": 0,
        "c4": 2,
        "c6": 3,
        "method": "c",
        "fielder": "ibrahim",
        "bowler": 294,
        "not_out": false
      },
      {
        "id": 36,
        "batted": true,
        "pos": 8,
        "runs": 16,
        "balls": 13,
        "c0": 6,
        "c1": 4,
        "c2": 0,
        "c3": 0,
        "c4": 3,
        "c6": 0,
        "method": "b",
        "fielder": null,
        "bowler": 294,
        "not_out": false
      },
      {
        "id": 35,
        "batted": true,
        "pos": 9,
        "runs": 7,
        "balls": 7,
        "c0": 3,
        "c1": 3,
        "c2": 0,
        "c3": 0,
        "c4": 1,
        "c6": 0,
        "method": "b",
        "fielder": null,
        "bowler": 294,
        "not_out": false
      },
      {
        "id": 39,
        "batted": true,
        "pos": 10,
        "runs": 10,
        "balls": 4,
        "c0": 0,
        "c1": 2,
        "c2": 0,
        "c3": 0,
        "c4": 2,
        "c6": 0,
        "method": null,
        "fielder": null,
        "bowler": null,
        "not_out": true
      },
      {
        "id": 198,
        "batted": true,
        "pos": 11,
        "runs": 1,
        "balls": 3,
        "c0": 2,
        "c1": 1,
        "c2": 0,
        "c3": 0,
        "c4": 0,
        "c6": 0,
        "method": "c",
        "fielder": "nabi",
        "bowler": 294,
        "not_out": false
      }
    ],
    "spells": [
      {
        "bowler": 164,
        "overs": 3.0,
        "runs": 29,
        "wickets": 2
      },
      {
        "bowler": 294,
        "overs": 4.0,
        "runs": 21,
        "wickets": 4
      },
      {
        "bowler": 295,
        "overs": 3.0,
        "runs": 22,
        "wickets": 0
      },
      {
        "bowler": 344,
        "overs": 2.0,
        "runs": 15,
        "wickets": 0
      },
      {
        "bowler": 113,
        "overs": 4.0,
        "runs": 23,
        "wickets": 1
      },
      {
        "bowler": 112,
        "overs": 4.0,
        "runs": 32,
        "wickets": 3
      }
    ]
  },
  "inn2": {
    "score": 143,
    "for": 5,
    "overs": 19.2,
    "extras": {
      "total_extras": 2,
      "wides": 1,
      "no_balls": 1,
      "lbs": 0,
      "byes": 0
    },
    "batting": [
      {
        "id": 288,
        "batted": true,
        "pos": 1,
        "runs": 26,
        "balls": 24,
        "c0": 12,
        "c1": 8,
        "c2": 0,
        "c3": 0,
        "c4": 3,
        "c6": 1,
        "method": "b",
        "fielder": null,
        "bowler": 35,
        "not_out": false
      },
      {
        "id": 290,
        "batted": true,
        "pos": 2,
        "runs": 55,
        "balls": 42,
        "c0": 8,
        "c1": 27,
        "c2": 0,
        "c3": 0,
        "c4": 7,
        "c6": 0,
        "method": "b",
        "fielder": null,
        "bowler": 35,
        "not_out": false
      },
      {
        "id": 343,
        "batted": true,
        "pos": 3,
        "runs": 24,
        "balls": 23,
        "c0": 10,
        "c1": 10,
        "c2": 0,
        "c3": 0,
        "c4": 2,
        "c6": 1,
        "method": "b",
        "fielder": null,
        "bowler": 208,
        "not_out": false
      },
      {
        "id": 342,
        "batted": true,
        "pos": 4,
        "runs": 0,
        "balls": 1,
        "c0": 1,
        "c1": 0,
        "c2": 0,
        "c3": 0,
        "c4": 0,
        "c6": 0,
        "method": "b",
        "fielder": null,
        "bowler": 208,
        "not_out": false
      },
      {
        "id": 344,
        "batted": true,
        "pos": 5,
        "runs": 16,
        "balls": 11,
        "c0": 4,
        "c1": 4,
        "c2": 1,
        "c3": 0,
        "c4": 1,
        "c6": 1,
        "method": "lbw",
        "fielder": null,
        "bowler": 208,
        "not_out": false
      },
      {
        "id": 113,
        "batted": true,
        "pos": 6,
        "runs": 20,
        "balls": 15,
        "c0": 4,
        "c1": 8,
        "c2": 0,
        "c3": 0,
        "c4": 3,
        "c6": 0,
        "method": null,
        "fielder": null,
        "bowler": null,
        "not_out": true
      },
      {
        "id": 112,
        "batted": true,
        "pos": 7,
        "runs": 0,
        "balls": 1,
        "c0": 1,
        "c1": 0,
        "c2": 0,
        "c3": 0,
        "c4": 0,
        "c6": 0,
        "method": null,
        "fielder": null,
        "bowler": null,
        "not_out": true
      },
      {
        "id": 345,
        "batted": false
      },
      {
        "id": 164,
        "batted": false
      },
      {
        "id": 294,
        "batted": false
      },
      {
        "id": 295,
        "batted": false
      }
    ],
    "spells": [
      {
        "bowler": 36,
        "overs": 3.0,
        "runs": 23,
        "wickets": 0
      },
      {
        "bowler": 198,
        "overs": 3.2,
        "runs": 30,
        "wickets": 0
      },
      {
        "bowler": 35,
        "overs": 4.0,
        "runs": 21,
        "wickets": 2
      },
      {
        "bowler": 32,
        "overs": 1.0,
        "runs": 14,
        "wickets": 0
      },
      {
        "bowler": 39,
        "overs": 4.0,
        "runs": 28,
        "wickets": 0
      },
      {
        "bowler": 208,
        "overs": 4.0,
        "runs": 27,
        "wickets": 3
      }
    ]
  }
}